chtoolbox/__init__.py
chtoolbox/add_license.py
chtoolbox/misc.py
chtoolbox/testing.py
tests/__init__.py
tests/test_testing.py
chtoolbox-1.2.0.dist-info/LICENSE
chtoolbox-1.2.0.dist-info/METADATA
chtoolbox-1.2.0.dist-info/WHEEL
chtoolbox-1.2.0.dist-info/top_level.txt
chtoolbox-1.2.0.dist-info/RECORD
