Metadata-Version: 2.1
Name: chtoolbox
Version: 1.2.0
Home-page: https://github.com/chagenvik/chtoolbox
License-File: LICENSE
Requires-Dist: numpy>=1.26.2
Requires-Dist: pandas>=2.1.4
Requires-Dist: pathspec>=0.12.1
